<?xml version="1.0" encoding="UTF-8"?>
<odoo>
	<data>
<!-- 		<template id="add_wineshop_pager_inherit" -->
<!-- 			inherit_id="website_sale.products" name="Wineshop Top Panel" -->
<!-- 			customize_show="True" active="True" priority="10"> -->
<!-- 			<xpath -->
<!-- 				expr="//div[hasclass('o_wsale_products_grid_table_wrapper')]" -->
<!-- 				position="before"> -->
				
				<template id="custom_code_layout_inherit" name="Custom Code Layout" inherit_id="website.layout" priority="55">
    			<xpath expr="//head" position="inside">
				<style>
					.circle {
					
                    font: bold 15px Sans-Serif;
                    color: white;
                    text-align: center;
                    position: absolute;
                    padding: 7px 0; left: 300px; top: 15px;
                    width: 200px;

                }
					}
				</style>
				<div class="circle">

					<span>Our Kitchen is busy at this time and orders may be longer
						than expected.
					</span>
				</div>
			</xpath>
		</template>
	</data>
</odoo>